langchain_dolphindb/__init__.py
langchain_dolphindb/vector_store.py
langchain_dolphindb-0.0.1.dist-info/LICENSE
langchain_dolphindb-0.0.1.dist-info/METADATA
langchain_dolphindb-0.0.1.dist-info/WHEEL
langchain_dolphindb-0.0.1.dist-info/RECORD
