Metadata-Version: 2.3
Name: langchain-dolphindb
Version: 0.0.1
Summary: Langchain integration for DolphinDB Vector Store
Author: DolphinDB, Inc.
Author-email: it@dolphindb.com
Requires-Python: >=3.9
Classifier: Programming Language :: Python :: 3
Classifier: Programming Language :: Python :: 3.9
Classifier: Programming Language :: Python :: 3.10
Classifier: Programming Language :: Python :: 3.11
Classifier: Programming Language :: Python :: 3.12
Classifier: Programming Language :: Python :: 3.13
Requires-Dist: dolphindb (>=3.0)
Requires-Dist: langchain-core (>=0.3,<0.4.0)
Requires-Dist: numpy (>=1.19.5,<2.0.0)
Requires-Dist: pandas (>=1.0.0)
Requires-Dist: pydantic-settings (>=2.4.0,<3.0.0)
